odoo8_addon_res_partner_attributes_add_NEQ-8.0.1.0.0.99.dev5-py2.7-nspkg.pth
odoo8_addon_res_partner_attributes_add_NEQ-8.0.1.0.0.99.dev5.dist-info/METADATA
odoo8_addon_res_partner_attributes_add_NEQ-8.0.1.0.0.99.dev5.dist-info/RECORD
odoo8_addon_res_partner_attributes_add_NEQ-8.0.1.0.0.99.dev5.dist-info/WHEEL
odoo8_addon_res_partner_attributes_add_NEQ-8.0.1.0.0.99.dev5.dist-info/namespace_packages.txt
odoo8_addon_res_partner_attributes_add_NEQ-8.0.1.0.0.99.dev5.dist-info/top_level.txt
odoo_addons/res_partner_attributes_add_NEQ/README.rst
odoo_addons/res_partner_attributes_add_NEQ/__init__.py
odoo_addons/res_partner_attributes_add_NEQ/__openerp__.py
odoo_addons/res_partner_attributes_add_NEQ/i18n/fr.po
odoo_addons/res_partner_attributes_add_NEQ/i18n/fr_CA.po
odoo_addons/res_partner_attributes_add_NEQ/i18n/nb_NO.po
odoo_addons/res_partner_attributes_add_NEQ/i18n/res_partner_attributes_add_NEQ.pot
odoo_addons/res_partner_attributes_add_NEQ/i18n/sl.po
odoo_addons/res_partner_attributes_add_NEQ/models/__init__.py
odoo_addons/res_partner_attributes_add_NEQ/models/res_partner.py
odoo_addons/res_partner_attributes_add_NEQ/static/description/icon.png
odoo_addons/res_partner_attributes_add_NEQ/views/res_partner.xml
